pydynpd/__init__.py
pydynpd/__version__.py
pydynpd/command.py
pydynpd/common_functions.py
pydynpd/dynamic_panel_model.py
pydynpd/info.py
pydynpd/instruments.py
pydynpd/model_organizer.py
pydynpd/model_summary.py
pydynpd/panel_data.py
pydynpd/regression.py
pydynpd/specification_tests.py
pydynpd/variable.py
pydynpd-0.2.1.dist-info/LICENSE
pydynpd-0.2.1.dist-info/METADATA
pydynpd-0.2.1.dist-info/WHEEL
pydynpd-0.2.1.dist-info/top_level.txt
pydynpd-0.2.1.dist-info/RECORD
