Metadata-Version: 2.1
Name: pydynpd
Version: 0.2.1
Summary: A package to estimate dynamic panel data model using difference GMM and system GMM.
Home-page: https://github.com/dazhwu/pydynpd
Author: Dazhong Wu
Author-email: wudz800@gmail.com
License: MIT
Classifier: License :: OSI Approved :: MIT License
Classifier: Programming Language :: Python
Classifier: Programming Language :: Python :: 3
Classifier: Programming Language :: Python :: 3.6
Classifier: Programming Language :: Python :: Implementation :: CPython
Classifier: Programming Language :: Python :: Implementation :: PyPy
Requires-Python: >=3.6.0
License-File: LICENSE
Requires-Dist: numpy
Requires-Dist: scipy
Requires-Dist: prettytable
Requires-Dist: pandas
